single_transmon/Transmon.py
single_transmon/__init__.py
transmon_chain/ChainTwoToneSimulation.py
transmon_chain/TransmonChain.py
transmon_chain/UnperturbedChainSpectrumSimulation.py
transmon_chain/__init__.py
two_transmons/ATSplittingSimulation.py
two_transmons/DoubleTransmonSystem.py
two_transmons/Rabi.py
two_transmons/ReadoutResonator.py
two_transmons/Sidebands.py
two_transmons/Tomography.py
two_transmons/TransmonControl.py
two_transmons/TwoToneSimulation.py
two_transmons/VacuumRabiSimulation.py
two_transmons/ZPulse.py
two_transmons/__init__.py
transmon_simulations-0.1.3.dist-info/METADATA
transmon_simulations-0.1.3.dist-info/WHEEL
transmon_simulations-0.1.3.dist-info/top_level.txt
transmon_simulations-0.1.3.dist-info/RECORD
