Metadata-Version: 2.1
Name: transmon-simulations
Version: 0.1.3
Summary: Transmon simulations module
Home-page: https://github.com/vdrhtc/Examples/transmon_simulations
Author: Gleb Fedorov
Author-email: vdrhtc@gmail.com
License: UNKNOWN
Platform: UNKNOWN
Classifier: Programming Language :: Python :: 3
Classifier: License :: OSI Approved :: GNU General Public License v3 (GPLv3)
Classifier: Operating System :: OS Independent
